MANIFEST.in
README.rst
setup.cfg
setup.py
examples/__init__.py
examples/trigger_skeleton.py
mongoop/__init__.py
mongoop/__init__.pyc
mongoop/cli.py
mongoop/cli.pyc
mongoop/core.py
mongoop/core.pyc
mongoop/default_settings.py
mongoop/default_settings.pyc
mongoop.egg-info/PKG-INFO
mongoop.egg-info/SOURCES.txt
mongoop.egg-info/dependency_links.txt
mongoop.egg-info/entry_points.txt
mongoop.egg-info/pbr.json
mongoop.egg-info/requires.txt
mongoop.egg-info/top_level.txt
mongoop/triggers/.nsca.py.swp
mongoop/triggers/__init__.py
mongoop/triggers/__init__.pyc
mongoop/triggers/email.py
mongoop/triggers/email.pyc
mongoop/triggers/graphite.py
mongoop/triggers/killer.py
mongoop/triggers/killer.pyc
mongoop/triggers/mattermost.py
mongoop/triggers/mongodb.py
mongoop/triggers/mongodb.pyc
mongoop/triggers/nsca.pyc
mongoop/triggers/sentry.py
mongoop/triggers/webhook.py
mongoop/triggers/webhook.pyc
mongoop/triggers/templates/email.j2
mongoop/triggers/templates/email_balancer.j2