Metadata-Version: 1.1
Name: mongoop
Version: 0.6
Summary: Monitor and locate long running operations on MongoDB and automatically trigger specific actions for alerting and performance analysis.
Home-page: https://github.com/lujeni/mongoop
Author: Lujeni
Author-email: julien@thebault.co
License: BSD
Download-URL: https://github.com/lujeni/mongoop/tags
Platform: any
Classifier: License :: OSI Approved :: BSD License
Classifier: Operating System :: POSIX :: Linux
Classifier: Programming Language :: Python
Classifier: Programming Language :: Python :: 2.7
Classifier: Topic :: Software Development :: Libraries :: Python Modules
